{
  "version": "7",
  "dialect": "sqlite",
  "entries": [
    {
      "idx": 0,
      "version": "6",
      "when": 1773238422899,
      "tag": "0000_great_squadron_supreme",
      "breakpoints": true
    },
    {
      "idx": 1,
      "version": "6",
      "when": 1774114086130,
      "tag": "0001_noisy_mach_iv",
      "breakpoints": true
    },
    {
      "idx": 2,
      "version": "6",
      "when": 1774137918675,
      "tag": "0002_tiny_human_cannonball",
      "breakpoints": true
    }
  ]
}